mapa/__init__.py
mapa/algorithm.py
mapa/caching.py
mapa/cli.py
mapa/conf.py
mapa/exceptions.py
mapa/map.py
mapa/mapa.ipynb
mapa/raster.py
mapa/stac.py
mapa/stl_file.py
mapa/tiling.py
mapa/utils.py
mapa/verification.py
mapa/zip.py
mapa-0.13.0.dist-info/LICENSE
mapa-0.13.0.dist-info/METADATA
mapa-0.13.0.dist-info/WHEEL
mapa-0.13.0.dist-info/entry_points.txt
mapa-0.13.0.dist-info/RECORD
