Metadata-Version: 2.1
Name: mapa
Version: 0.13.0
Summary: 🌍 Create 3d-printable STLs from satellite elevation data 🌏
Home-page: https://github.com/fgebhart/mapa
Author: Fabian Gebhart
Requires-Python: >=3.10,<3.11
Classifier: License :: OSI Approved :: MIT License
Classifier: Operating System :: MacOS
Classifier: Operating System :: POSIX :: Linux
Classifier: Programming Language :: Python
Classifier: Programming Language :: Python :: 3
Classifier: Programming Language :: Python :: 3.10
Classifier: Programming Language :: Python :: 3.8
Classifier: Programming Language :: Python :: 3.9
Requires-Dist: click (>=8.1.3,<9.0.0)
Requires-Dist: geojson (>=3.0.1,<4.0.0)
Requires-Dist: haversine (>=2.8.0,<3.0.0)
Requires-Dist: ipyleaflet (==0.13.3)
Requires-Dist: notebook (>=6.5.3,<7.0.0)
Requires-Dist: numba (>=0.56.4,<0.57.0)
Requires-Dist: numpy (>=1.23,<2.0)
Requires-Dist: numpy-stl (>=3.0.1,<4.0.0)
Requires-Dist: planetary-computer (>=1.0.0,<2.0.0)
Requires-Dist: pystac-client (>=0.8.5,<0.9.0)
Requires-Dist: rasterio (>=1.3.6,<2.0.0)
Project-URL: Repository, https://github.com/fgebhart/mapa
